yandex_neural_api/__init__.py
yandex_neural_api/client.py
yandex_neural_api/tests.py
yandex_neural_api-0.0.2.dist-info/METADATA
yandex_neural_api-0.0.2.dist-info/WHEEL
yandex_neural_api-0.0.2.dist-info/licenses/LICENSE
yandex_neural_api-0.0.2.dist-info/RECORD
