Metadata-Version: 2.3
Name: yandex-neural-api
Version: 0.0.2
Summary: A Python client for Yandex Neural API
Project-URL: Homepage, https://github.com/daswer123/yandex-neural-api
Project-URL: Bug Tracker, https://github.com/daswer123/yandex-neural-api/issues
Author-email: daswer123 <daswerq123@gmail.com>
License-File: LICENSE
Classifier: License :: OSI Approved :: MIT License
Classifier: Operating System :: OS Independent
Classifier: Programming Language :: Python :: 3
Requires-Python: >=3.9
Requires-Dist: aiohttp
Requires-Dist: requests
